[
  {
    "sono": "１",
    "date": "令和８年３月23日",
    "category": "医科",
    "topic": "抗菌薬適正使用体制加算",
    "question_no": "１",
    "question": "「Ａ０００」初診料の注 14 及び「Ａ００１」再診料の注 18 に規定する抗菌薬適正使用体制加算の施設基準における確認方法はどうすればよいか。",
    "answer": "Ｊ－ＳＩＰＨＥ及び診療所版Ｊ－ＳＩＰＨＥにおいて、四半期ごとに抗菌薬の使用状況に関するデータの提出を受け付け、結果に基づき判断する。",
    "source_url": "https://www.mhlw.go.jp/content/12400000/001678310.pdf"
  },
  {
    "sono": "１",
    "date": "令和８年３月23日",
    "category": "医科",
    "topic": "抗菌薬適正使用体制加算",
    "question_no": "２",
    "question": "問１について、Access 抗菌薬に分類されるものの使用比率は、具体的にはどのように計算されるのか。",
    "answer": "各抗菌薬の Access 抗菌薬への該当性並びに使用比率に係るＪ－ＳＩＰＨＥ及び診療所版Ｊ－ＳＩＰＨＥにおける計算方法については、ホームページを確認すること。",
    "source_url": "https://www.mhlw.go.jp/content/12400000/001678310.pdf"
  },
  {
    "sono": "１",
    "date": "令和８年３月23日",
    "category": "医科",
    "topic": "電子的診療情報連携体制整備加算",
    "question_no": "３",
    "question": "令和８年５月 31 日において現に医療ＤＸ推進体制整備加算及び診療録管理体制加算の施設基準を届け出ている保険医療機関が、同年６月１日以降に電子的診療情報連携体制整備加算を算定する場合は、改めて届出を行う必要があるか。",
    "answer": "改めて届出を行う必要がある。",
    "source_url": "https://www.mhlw.go.jp/content/12400000/001678310.pdf"
  },
  {
    "sono": "１",
    "date": "令和８年３月23日",
    "category": "医科",
    "topic": "外来データ提出加算及び充実管理加算",
    "question_no": "４",
    "question": "既に生活習慣病管理料（Ⅰ）及び（Ⅱ）の注４に規定する充実管理加算に係る施設基準の届出を行っている医療機関において、新たに外来データ提出加算の施設基準の届出を行う場合、改めて様式７の 10 の届出を行う必要があるか。",
    "answer": "改めて様式７の 10 の届出を行う必要がある。",
    "source_url": "https://www.mhlw.go.jp/content/12400000/001678310.pdf"
  },
  {
    "sono": "１",
    "date": "令和８年３月23日",
    "category": "医科",
    "topic": "急性期病院一般入院基本料",
    "question_no": "12",
    "question": "「Ａ１００」急性期病院一般入院基本料の施設基準における研修とはどのような研修か。",
    "answer": "現時点では、日本看護協会認定看護管理者教育課程「サードレベル」を指す。",
    "source_url": "https://www.mhlw.go.jp/content/12400000/001678310.pdf"
  },
  {
    "sono": "１",
    "date": "令和８年３月23日",
    "category": "医科",
    "topic": "看護・多職種協働加算",
    "question_no": "13",
    "question": "看護・多職種協働加算は病棟ごとに届け出るのか。",
    "answer": "保険医療機関内の急性期病院Ｂ一般入院料又は急性期一般入院料４を算定する一般病棟全体で届け出ること。【回復期リハビリテーション病棟入院料、特定機能病院リハビリテーション病棟入院料】",
    "source_url": "https://www.mhlw.go.jp/content/12400000/001678310.pdf"
  },
  {
    "sono": "１",
    "date": "令和８年３月23日",
    "category": "医科",
    "topic": "看護・多職種協働加算",
    "question_no": "27",
    "question": "回復期リハビリテーション病棟入院料２及び４の要件として追加された「ＦＩＭの測定に係る研修」についても、同様に看護職員が対象となるか。",
    "answer": "同様である。ＦＩＭの測定を担当する看護職員も研修の対象とすること。",
    "source_url": "https://www.mhlw.go.jp/content/12400000/001678310.pdf"
  },
  {
    "sono": "１",
    "date": "令和８年３月23日",
    "category": "看護職員処遇改善・ベースアップ評価料",
    "topic": "ベースアップ評価料",
    "question_no": "１",
    "question": "令和８年３月 31 日時点において評価料を届け出ていた保険医療機関との規定について、令和８年４月から算定を開始する保険医療機関は含まれるのか。",
    "answer": "令和８年３月 31 日時点で当該評価料を算定している必要があることから、同年４月以降に算定を開始する保険医療機関は含まれない。",
    "source_url": "https://www.mhlw.go.jp/content/12400000/001678310.pdf"
  },
  {
    "sono": "１",
    "date": "令和８年３月23日",
    "category": "看護職員処遇改善・ベースアップ評価料",
    "topic": "ベースアップ評価料",
    "question_no": "２",
    "question": "看護職員処遇改善評価料を用いた賃金の改善措置の対象者及びベースアップ評価料の対象職員には、派遣職員も含むのか。",
    "answer": "一定の要件を満たす場合、派遣職員に限り対象とすることを可能とする。",
    "source_url": "https://www.mhlw.go.jp/content/12400000/001678310.pdf"
  },
  {
    "sono": "１",
    "date": "令和８年３月23日",
    "category": "看護職員処遇改善・ベースアップ評価料",
    "topic": "調剤ベースアップ評価料",
    "question_no": "３",
    "question": "管理薬剤師は当該評価料の賃金改善の対象職員となるか。",
    "answer": "対象とならない。",
    "source_url": "https://www.mhlw.go.jp/content/12400000/001678310.pdf"
  },
  {
    "sono": "１",
    "date": "令和８年３月23日",
    "category": "歯科",
    "topic": "初診料",
    "question_no": "１",
    "question": "初診料の施設基準に規定する、新興感染症に対する対策の研修について、「（抗菌薬の適正使用を含む。）」が追加されたが、どのような内容の研修が該当するのか。",
    "answer": "「抗微生物薬適正使用の手引き 第四版 歯科編」を参考にすること。",
    "source_url": "https://www.mhlw.go.jp/content/12400000/001678310.pdf"
  },
  {
    "sono": "１",
    "date": "令和８年３月23日",
    "category": "調剤",
    "topic": "地域支援・医薬品供給対応体制加算",
    "question_no": "１",
    "question": "地域支援・医薬品供給対応体制加算の施設基準のうち、算定回数の合計のみなし規定についてどう判断すればよいか。",
    "answer": "よい。令和９年６月１日までに行う届出にあたっては、旧点数表における算定回数の合計とみなす。",
    "source_url": "https://www.mhlw.go.jp/content/12400000/001678310.pdf"
  },
  {
    "sono": "１",
    "date": "令和８年３月23日",
    "category": "訪問看護",
    "topic": "訪問看護基本療養費等",
    "question_no": "１",
    "question": "同一建物居住者について、同一敷地内が含まれることとなったが、同一敷地内とはどのような場合が該当するか。",
    "answer": "同一地番の敷地内である場合や、公道に出ずに敷地を行き来できる等一体的に利用されている敷地である場合が該当する。",
    "source_url": "https://www.mhlw.go.jp/content/12400000/001678310.pdf"
  },
  {
    "sono": "２",
    "date": "令和８年４月１日",
    "category": "医科",
    "topic": "電子的診療情報連携体制整備加算",
    "question_no": "１",
    "question": "電子的診療情報連携体制整備加算の施設基準において、電子カルテ情報共有サービスとの接続インターフェースに関する要件をどう考えればよいか。",
    "answer": "施設基準のうち一定の項目を満たす場合には、当該要件を満たすものとみなす。",
    "source_url": "https://www.mhlw.go.jp/content/12400000/001689076.pdf"
  },
  {
    "sono": "２",
    "date": "令和８年４月１日",
    "category": "医科",
    "topic": "急性期病院一般入院基本料",
    "question_no": "２",
    "question": "急性期病院一般入院基本料の救急搬送及び全身麻酔の実績について、直近１年の実績で届出を行うのか。",
    "answer": "前年度の４月から３月までの直近１年間のデータで届出を行うこと。",
    "source_url": "https://www.mhlw.go.jp/content/12400000/001689076.pdf"
  },
  {
    "sono": "２",
    "date": "令和８年４月１日",
    "category": "医科",
    "topic": "医師事務作業補助体制加算",
    "question_no": "11",
    "question": "医師事務作業補助体制加算の施設基準における生成ＡＩを活用した文書作成補助システムの導入について、具体的にどのようなことを指すか。",
    "answer": "医師又は医師事務作業補助者の過半数が当該システムを少なくとも毎週使用していること等が該当する。",
    "source_url": "https://www.mhlw.go.jp/content/12400000/001689076.pdf"
  },
  {
    "sono": "２",
    "date": "令和８年４月１日",
    "category": "医科",
    "topic": "地域医療体制確保加算",
    "question_no": "15",
    "question": "地域医療体制確保加算２の施設基準に定める消化器外科、心臓血管外科、小児外科及び循環器内科とは、どのような診療科があてはまるのか。",
    "answer": "各特定診療科において、原則として当該特定診療科以外の診療科の診療を実施していないことが必要である。",
    "source_url": "https://www.mhlw.go.jp/content/12400000/001689076.pdf"
  },
  {
    "sono": "２",
    "date": "令和８年４月１日",
    "category": "医科",
    "topic": "心不全再入院予防継続管理料",
    "question_no": "54",
    "question": "心不全再入院予防継続管理料における「関係学会より示されているガイドライン」とは、具体的には何を指すのか。",
    "answer": "現時点では、日本循環器学会及び日本心不全学会の「心不全診療ガイドライン」を指す。",
    "source_url": "https://www.mhlw.go.jp/content/12400000/001689076.pdf"
  },
  {
    "sono": "２",
    "date": "令和８年４月１日",
    "category": "医科",
    "topic": "体外照射",
    "question_no": "97",
    "question": "体外照射の強度変調放射線治療（ＩＭＲＴ）の施設基準にある「関係学会の定めるガイドライン」とは具体的に何か。",
    "answer": "現時点では、日本放射線腫瘍学会の関連ガイドラインを指す。",
    "source_url": "https://www.mhlw.go.jp/content/12400000/001689076.pdf"
  },
  {
    "sono": "２",
    "date": "令和８年４月１日",
    "category": "看護職員処遇改善・ベースアップ評価料",
    "topic": "ベースアップ評価料",
    "question_no": "１",
    "question": "評価料を届け出ていた保険医療機関の規定について、令和８年４月から算定を開始する保険医療機関は含まれるのか。",
    "answer": "含まれない。",
    "source_url": "https://www.mhlw.go.jp/content/12400000/001689076.pdf"
  },
  {
    "sono": "２",
    "date": "令和８年４月１日",
    "category": "看護職員処遇改善・ベースアップ評価料",
    "topic": "調剤ベースアップ評価料",
    "question_no": "８",
    "question": "管理薬剤師はベースアップ評価料の賃金改善の対象職員となるか。",
    "answer": "対象とならない。",
    "source_url": "https://www.mhlw.go.jp/content/12400000/001689076.pdf"
  },
  {
    "sono": "２",
    "date": "令和８年４月１日",
    "category": "DPC",
    "topic": null,
    "question_no": "１－１",
    "question": "診療記録管理者とはどのような業務を行う者か。",
    "answer": "診療情報の管理等を行う診療情報管理士等をいう。２．ＤＰＣ対象患者について",
    "source_url": "https://www.mhlw.go.jp/content/12400000/001689076.pdf"
  },
  {
    "sono": "２",
    "date": "令和８年４月１日",
    "category": "DPC",
    "topic": null,
    "question_no": "２－１",
    "question": "ＤＰＣ対象患者は、自らの意志で診断群分類点数表と医科点数表のいずれにより算定するかを選択することができるのか。",
    "answer": "選択できない。",
    "source_url": "https://www.mhlw.go.jp/content/12400000/001689076.pdf"
  },
  {
    "sono": "２",
    "date": "令和８年４月１日",
    "category": "歯科",
    "topic": "地域歯科医療加算",
    "question_no": "１",
    "question": "地域歯科医療加算における「その他イ又はロに準ずるもの」とはどのようなものか。",
    "answer": "都道府県等からの委託等により行う巡回診療等が該当する。",
    "source_url": "https://www.mhlw.go.jp/content/12400000/001689076.pdf"
  },
  {
    "sono": "２",
    "date": "令和８年４月１日",
    "category": "調剤",
    "topic": "調剤基本料",
    "question_no": "１",
    "question": "医療モールの処方箋集中率の計算方法について、モールの外にある保険薬局にも適用されるのか。",
    "answer": "そのとおり。",
    "source_url": "https://www.mhlw.go.jp/content/12400000/001689076.pdf"
  },
  {
    "sono": "２",
    "date": "令和８年４月１日",
    "category": "訪問看護",
    "topic": "機能強化型訪問看護管理療養費",
    "question_no": "１",
    "question": "機能強化型訪問看護管理療養費４が新設されたが、既存の取扱いは同様となるのか。",
    "answer": "そのとおり。",
    "source_url": "https://www.mhlw.go.jp/content/12400000/001689076.pdf"
  }
]
